lazytensor/VERSION
lazytensor/__init__.py
lazytensor/base.py
lazytensor-0.1.0a2.dist-info/LICENSE
lazytensor-0.1.0a2.dist-info/METADATA
lazytensor-0.1.0a2.dist-info/WHEEL
lazytensor-0.1.0a2.dist-info/top_level.txt
lazytensor-0.1.0a2.dist-info/RECORD
